apps/BaseApp.py
apps/PiModelApp.py
apps/Registry.py
apps/SingleModelApp.py
apps/__init__.py
datasets/BaseDataframeDataset.py
datasets/DataframeImageCategoricalDataset.py
datasets/Registry.py
datasets/__init__.py
loss_functions/EntropyLoss.py
loss_functions/VATLoss.py
loss_functions/__init__.py
manager/Manager.py
manager/__init__.py
mlops/MLOpsTask.py
mlops/__init__.py
postprocessors/BasePostProcessor.py
postprocessors/DataframeImageCategoricalPostprocessor.py
postprocessors/Registry.py
postprocessors/__init__.py
trainer/Trainer.py
trainer/__init__.py
utils/DatasetSplitter.py
utils/RunMode.py
utils/__init__.py
utils/constants.py
utils/dataset_utils.py
utils/dicom_utils.py
utils/image_utils.py
utils/mask_utils.py
utils/metrics.py
utils/plots_matplotlib.py
utils/plots_mlops.py
utils/plots_opencv.py
utils/registry.py
utils/training.py
utils/transforms.py
simple_converge-0.11.0.dist-info/LICENSE.txt
simple_converge-0.11.0.dist-info/METADATA
simple_converge-0.11.0.dist-info/WHEEL
simple_converge-0.11.0.dist-info/top_level.txt
simple_converge-0.11.0.dist-info/RECORD
